{
  "users": [],
  "vehicles": [
    {
      "id": 1,
      "vin": "2T1BURHE0JC044186",
      "year": 2018,
      "make": "TOYOTA",
      "model": "Corolla",
      "color": "",
      "bodyType": "Sedan/Saloon",
      "engineType": "",
      "transmission": "",
      "driveType": "4x2",
      "gvwr": "",
      "plant": "CANADA",
      "rawData": null,
      "scannedAt": "2026-06-22T21:10:43.211Z"
    }
  ],
  "services": [
    {
      "id": 1,
      "name": "Paint Correction",
      "price": 150
    },
    {
      "id": 2,
      "name": "Ceramic Coating",
      "price": 500
    },
    {
      "id": 3,
      "name": "Interior Detailing",
      "price": 200
    },
    {
      "id": 4,
      "name": "Exterior Wash",
      "price": 75
    },
    {
      "id": 5,
      "name": "Wax Application",
      "price": 100
    }
  ],
  "invoices": [],
  "customers": [],
  "businessSettings": {
    "businessName": "Your Detailing Business",
    "address": "123 Main Street",
    "city": "Your City",
    "state": "State",
    "zipCode": "12345",
    "phone": "(555) 123-4567",
    "email": "info@yourdetailing.com",
    "taxRate": 8,
    "invoicePrefix": "INV",
    "paymentTerms": 14,
    "currency": "$",
    "logo": null
  }
}